{
  "$schema": "https://raw.githubusercontent.com/spdx/spdx-spec/v2.2.1/schemas/spdx-schema.json",
  "spdxVersion": "SPDX-2.2",
  "dataLicense": "CC0-1.0",
  "SPDXID": "SPDXRef-DOCUMENT",
  "documentNamespace": "https://spdx.org/spdxdocs/boost-headers-x64-windows-1.85.0#1-73bd793f-5a7e-4bef-8fe6-3fa53123c957",
  "name": "boost-headers:x64-windows@1.85.0#1 868c063a9e5a093522eedda40be89fd91e5215c88403f016f8103210ed18fa1b",
  "creationInfo": {
    "creators": [
      "Tool: vcpkg-2024-09-18-5f5da308dd1dd3cc49641c60eafff176e248a9dd"
    ],
    "created": "2024-09-30T20:38:58Z"
  },
  "relationships": [
    {
      "spdxElementId": "SPDXRef-port",
      "relationshipType": "GENERATES",
      "relatedSpdxElement": "SPDXRef-binary"
    },
    {
      "spdxElementId": "SPDXRef-port",
      "relationshipType": "CONTAINS",
      "relatedSpdxElement": "SPDXRef-file-0"
    },
    {
      "spdxElementId": "SPDXRef-port",
      "relationshipType": "CONTAINS",
      "relatedSpdxElement": "SPDXRef-file-1"
    },
    {
      "spdxElementId": "SPDXRef-binary",
      "relationshipType": "GENERATED_FROM",
      "relatedSpdxElement": "SPDXRef-port"
    },
    {
      "spdxElementId": "SPDXRef-file-0",
      "relationshipType": "CONTAINED_BY",
      "relatedSpdxElement": "SPDXRef-port"
    },
    {
      "spdxElementId": "SPDXRef-file-1",
      "relationshipType": "CONTAINED_BY",
      "relatedSpdxElement": "SPDXRef-port"
    }
  ],
  "packages": [
    {
      "name": "boost-headers",
      "SPDXID": "SPDXRef-port",
      "versionInfo": "1.85.0#1",
      "downloadLocation": "git+https://github.com/Microsoft/vcpkg@dc074dbcbe8adaf7970a9dc92d8c385267042e0c",
      "homepage": "https://www.boost.org/libs/headers",
      "licenseConcluded": "BSL-1.0",
      "licenseDeclared": "NOASSERTION",
      "copyrightText": "NOASSERTION",
      "description": "Boost headers module",
      "comment": "This is the port (recipe) consumed by vcpkg."
    },
    {
      "name": "boost-headers:x64-windows",
      "SPDXID": "SPDXRef-binary",
      "versionInfo": "868c063a9e5a093522eedda40be89fd91e5215c88403f016f8103210ed18fa1b",
      "downloadLocation": "NONE",
      "licenseConcluded": "BSL-1.0",
      "licenseDeclared": "NOASSERTION",
      "copyrightText": "NOASSERTION",
      "comment": "This is a binary package built by vcpkg."
    },
    {
      "SPDXID": "SPDXRef-resource-1",
      "name": "boostorg/headers",
      "downloadLocation": "git+https://github.com/boostorg/headers@boost-1.85.0",
      "licenseConcluded": "NOASSERTION",
      "licenseDeclared": "NOASSERTION",
      "copyrightText": "NOASSERTION",
      "checksums": [
        {
          "algorithm": "SHA512",
          "checksumValue": "6b9b8f669b5692a5fa97c591f11163ca0a37733662904a39e708194c910e1de362585275d26babeda0fe7eccec42a88661849efd194090d452a182fade9ea156"
        }
      ]
    }
  ],
  "files": [
    {
      "fileName": "./C:/Users/s/.vcpkg-clion/vcpkg/buildtrees/versioning_/versions/boost-headers/dc074dbcbe8adaf7970a9dc92d8c385267042e0c/portfile.cmake",
      "SPDXID": "SPDXRef-file-0",
      "checksums": [
        {
          "algorithm": "SHA256",
          "checksumValue": "64f546fb5cf4db8d4c98405dc4168e803db7413edd48e2ef3a6403c683bb3c16"
        }
      ],
      "licenseConcluded": "NOASSERTION",
      "copyrightText": "NOASSERTION"
    },
    {
      "fileName": "./C:/Users/s/.vcpkg-clion/vcpkg/buildtrees/versioning_/versions/boost-headers/dc074dbcbe8adaf7970a9dc92d8c385267042e0c/vcpkg.json",
      "SPDXID": "SPDXRef-file-1",
      "checksums": [
        {
          "algorithm": "SHA256",
          "checksumValue": "7a16adf438dae9b2c59ee5457a551f656fdd373c7088aed882a9acdf1608063f"
        }
      ],
      "licenseConcluded": "NOASSERTION",
      "copyrightText": "NOASSERTION"
    }
  ]
}
